Workbook

Sheet Read Me
A1: MALTRA FOOD GROCER | ACCOUNTANT PORTFOLIO
A2: Independent fictional case study | September 2026 | AUD | prepared for skills demonstration
A4: Purpose
A5: Demonstrates month-end close, management reporting, reconciliations, inventory/COGS, fixed assets, CAPEX, audit/ABS support, multi-entity controls and process improvement.
A7: Important data disclaimer
A8: Maltra Food Grocer is a fictional portfolio case study. All entities, balances, transactions, dates, results and scenarios are illustrative and not actual company information. This work is not affiliated with Maltra Foods or Robert Half and should not be presented as employment work or a live company's records.
A11: How to use the portfolio
A13: Workbook area | B13: Purpose
A14: 1. Dashboard | B14: Start with the headline KPIs, financial performance and open exceptions.
A15: 2. Monthly P&L | B15: Review entity-level actual vs budget and explain variances using evidence, not assumptions.
A16: 3. GL Reconciliation | B16: Resolve items by cause, action, evidence and reviewer approval; formulas flag residual differences.
A17: 4. Intercompany | B17: Use opposite-sign balances and net differences to identify mismatches before consolidation.
A18: 5. Inventory & COGS | B18: Review stock roll-forward by manufacturing/grocery category; reconcile to subledger and GL.
A19: 6. Fixed Assets | B19: Review monthly depreciation and net book value; assumptions are simplified and must align to policy.
A20: 7. CAPEX Analysis | B20: Track approved budget, actuals, commitments, forecast remaining and utilisation.
A21: 8. Close Checklist | B21: Use owners, due dates, evidence and status to manage a controlled close.
A22: 9. Journal Register | B22: Review balanced illustrative journals; posting requires approval and source evidence.
A23: 10. Audit & ABS | B23: Track evidence requests and validate the applicable ABS survey instructions before any real submission.
A24: 11. Process Improvement | B24: Prioritise measurable changes; benefits are hypotheses until baselined and tested.
A25: 12. PowerBI Data | B25: Long-format fact table for importing into Power BI; build relationships/measures as described in the guide.

Sheet Dashboard
A1: MALTRA FOOD GROCER | FINANCE OPERATIONS DASHBOARD
A2: September 2026 | illustrative management view | amounts in AUD
A4: Revenue actual | B4: ='Monthly P&L'!B9 | D4: Revenue budget | E4: ='Monthly P&L'!C9
A7: EBITDA actual | B7: ='Monthly P&L'!L9 | D7: EBITDA budget | E7: ='Monthly P&L'!M9
A10: CAPEX utilisation | B10: ='CAPEX Analysis'!H11 | D10: Fixed asset NBV | E10: ='Fixed Assets'!K12
A13: Open / pending reconciliations | B13: =COUNTIF('GL Reconciliation'!H5:H10,"<>Reconciled") | D13: Close completion | E13: ='Close Checklist'!B15
A16: Management focus
A17: 1. Validate revenue and EBITDA variance drivers by entity; do not infer causes from totals alone.
A18: 2. Resolve inventory and accrual reconciling items with source evidence before sign-off.
A19: 3. Investigate the $3,000 intercompany mismatch before consolidation.
A20: 4. Review CAPEX utilisation and committed spend against approved budgets.
A21: 5. Complete close tasks with evidence and reviewer approval; no unsupported journals.

Sheet Monthly P&L
A1: MONTHLY P&L | ACTUAL VS BUDGET
A2: September 2026 | fictional multi-entity consumer goods group | AUD | management view before any consolidation eliminations
A4: Entity | B4: Revenue Actual | C4: Revenue Budget | D4: Revenue Var | E4: Revenue Var % | F4: COGS Actual | G4: COGS Budget | H4: COGS Var | I4: Opex Actual | J4: Opex Budget | K4: Opex Var | L4: EBITDA Actual | M4: EBITDA Budget | N4: EBITDA Var | O4: EBITDA Margin
A5: VIC Manufacturing | B5: 2450000 | C5: 2380000 | D5: =B5-C5 | E5: =IFERROR(D5/C5,0) | F5: 1470000 | G5: 1428000 | H5: =F5-G5 | I5: 510000 | J5: 495000 | K5: =I5-J5 | L5: =B5-F5-I5 | M5: =C5-G5-J5 | N5: =L5-M5 | O5: =IFERROR(L5/B5,0)
A6: NSW Distribution | B6: 1280000 | C6: 1320000 | D6: =B6-C6 | E6: =IFERROR(D6/C6,0) | F6: 806000 | G6: 831600 | H6: =F6-G6 | I6: 284000 | J6: 290000 | K6: =I6-J6 | L6: =B6-F6-I6 | M6: =C6-G6-J6 | N6: =L6-M6 | O6: =IFERROR(L6/B6,0)
A7: QLD Sales & Distribution | B7: 940000 | C7: 900000 | D7: =B7-C7 | E7: =IFERROR(D7/C7,0) | F7: 611000 | G7: 585000 | H7: =F7-G7 | I7: 205000 | J7: 198000 | K7: =I7-J7 | L7: =B7-F7-I7 | M7: =C7-G7-J7 | N7: =L7-M7 | O7: =IFERROR(L7/B7,0)
A8: Group Head Office | B8: 120000 | C8: 100000 | D8: =B8-C8 | E8: =IFERROR(D8/C8,0) | F8: 0 | G8: 0 | H8: =F8-G8 | I8: 365000 | J8: 350000 | K8: =I8-J8 | L8: =B8-F8-I8 | M8: =C8-G8-J8 | N8: =L8-M8 | O8: =IFERROR(L8/B8,0)
A9: Group total (pre-elimination) | B9: =SUM(B5:B8) | C9: =SUM(C5:C8) | D9: =SUM(D5:D8) | E9: =IFERROR(D9/C9,0) | F9: =SUM(F5:F8) | G9: =SUM(G5:G8) | H9: =SUM(H5:H8) | I9: =SUM(I5:I8) | J9: =SUM(J5:J8) | K9: =SUM(K5:K8) | L9: =SUM(L5:L8) | M9: =SUM(M5:M8) | N9: =SUM(N5:N8) | O9: =IFERROR(L9/B9,0)
A12: Metric | B12: Actual | C12: Budget | D12: Variance | E12: Variance % | F12: Commentary / investigation | G12: Owner action
A13: Revenue | B13: =B9 | C13: =C9 | D13: =B13-C13 | E13: =IFERROR(D13/C13,0) | F13: Revenue is above budget; validate price, volume, mix, timing and any intercompany revenue before attributing cause. | G13: Management Accountant: bridge by entity, customer/channel and product category.
A14: COGS | B14: =F9 | C14: =G9 | D14: =B14-C14 | E14: =IFERROR(D14/C14,0) | F14: COGS variance is adverse; investigate ingredient/stock costs, production yield, inventory adjustments and cut-off. | G14: Inventory Finance: reconcile inventory movements and quantify cost/volume drivers.
A15: Operating expenses | B15: =I9 | C15: =J9 | D15: =B15-C15 | E15: =IFERROR(D15/C15,0) | F15: Opex variance is adverse; review GL detail, freight, utilities, repairs, labour and timing. | G15: Financial Accountant: identify top accounts and classify recurring vs one-off.
A16: EBITDA | B16: =L9 | C16: =M9 | D16: =B16-C16 | E16: =IFERROR(D16/C16,0) | F16: EBITDA is a management metric and not a substitute for statutory profit or cash flow. | G16: Financial Controller: review material variances and approve reporting commentary.

Sheet GL Reconciliation
A1: BALANCE SHEET RECONCILIATION
A2: Illustrative account recs | difference = GL balance less adjusted support | no sign-off while unexplained differences remain
A4: Entity | B4: Account | C4: GL Balance | D4: Support Balance | E4: Known Reconciling Item (+/-) | F4: Adjusted Support | G4: Residual Difference | H4: Status | I4: Root Cause / Hypothesis | J4: Proposed Action | K4: Evidence Ref | L4: Preparer | M4: Reviewer Sign-off
A5: VIC Manufacturing | B5: Trade receivables | C5: 482500 | D5: 479800 | E5: 2700 | F5: =D5+E5 | G5: =C5-F5 | H5: =IF(ABS(G5)>=0.01,"Investigate",IF(M5="Approved","Reconciled","Pending review")) | I5: Cash receipt may be posted in GL but not allocated in AR subledger. | J5: Trace receipt to bank, remittance and customer account; post approved allocation if confirmed. | K5: AR-REC-SEP26-01 | L5: Accountant | M5: Pending
A6: VIC Manufacturing | B6: Inventory | C6: 735000 | D6: 742500 | E6: -7500 | F6: =D6+E6 | G6: =C6-F6 | H6: =IF(ABS(G6)>=0.01,"Investigate",IF(M6="Approved","Reconciled","Pending review")) | I6: Potential timing/stock adjustment mismatch; not confirmed. | J6: Tie count adjustment, goods in transit and stock movement cut-off to inventory subledger. | K6: INV-REC-SEP26-02 | L6: Inventory Accountant | M6: Pending
A7: NSW Distribution | B7: Trade payables | C7: -315400 | D7: -315400 | E7: 0 | F7: =D7+E7 | G7: =C7-F7 | H7: =IF(ABS(G7)>=0.01,"Investigate",IF(M7="Approved","Reconciled","Pending review")) | I7: No reconciling item identified in this illustrative example. | J7: Retain supplier statement and AP ageing; reviewer to verify completeness. | K7: AP-REC-SEP26-03 | L7: Accountant | M7: Pending
A8: QLD Sales & Distribution | B8: Bank | C8: 168250 | D8: 168250 | E8: 0 | F8: =D8+E8 | G8: =C8-F8 | H8: =IF(ABS(G8)>=0.01,"Investigate",IF(M8="Approved","Reconciled","Pending review")) | I8: No reconciling item identified in this illustrative example. | J8: Agree bank statement to ledger and verify outstanding items. | K8: BANK-REC-SEP26-04 | L8: Accountant | M8: Pending
A9: Group Head Office | B9: Accrued expenses | C9: -128000 | D9: -119500 | E9: -8500 | F9: =D9+E9 | G9: =C9-F9 | H9: =IF(ABS(G9)>=0.01,"Investigate",IF(M9="Approved","Reconciled","Pending review")) | I9: Possible missing accrual or sign convention issue; requires source validation. | J9: Inspect invoices received after close, service periods and prior-month reversals. | K9: ACCR-SEP26-05 | L9: Financial Accountant | M9: Pending
A10: VIC Manufacturing | B10: Fixed assets (cost) | C10: 2150000 | D10: 2150000 | E10: 0 | F10: =D10+E10 | G10: =C10-F10 | H10: =IF(ABS(G10)>=0.01,"Investigate",IF(M10="Approved","Reconciled","Pending review")) | I10: No reconciling item identified in this illustrative example. | J10: Tie register additions/disposals to GL and test selected invoices. | K10: FA-REC-SEP26-06 | L10: Financial Accountant | M10: Pending
A12: Control KPI | B12: Value
A13: Open / pending reconciliations | B13: =COUNTIF(H5:H10,"<>Reconciled")
A14: Total absolute residual difference | B14: =SUMPRODUCT(ABS(G5:G10))

Sheet Intercompany
A1: INTERCOMPANY BALANCE MATCHING
A2: Opposite-sign convention: Entity A balance + Entity B balance should equal zero
A4: Counterparty Pair | B4: Entity A Balance | C4: Entity B Balance (opposite sign) | D4: Net Difference | E4: Status | F4: Owner | G4: Action / Evidence
A5: Manufacturing ↔ Distribution | B5: 125000 | C5: -125000 | D5: =B5+C5 | E5: =IF(ABS(D5)<0.01,"Matched","Investigate") | F5: Group Accountant | G5: Tie to intercompany invoices and confirm both entities posted in the same period.
A6: Head Office ↔ Manufacturing | B6: 48000 | C6: -45000 | D6: =B6+C6 | E6: =IF(ABS(D6)<0.01,"Matched","Investigate") | F6: Financial Accountant | G6: Investigate $3,000 mismatch: check management-fee journal, period and tax treatment.
A7: Distribution ↔ QLD Sales | B7: -37500 | C7: 37500 | D7: =B7+C7 | E7: =IF(ABS(D7)<0.01,"Matched","Investigate") | F7: Group Accountant | G7: Confirm sign convention, transfer documentation and matching counterparty ledger.

Sheet Inventory & COGS
A1: INVENTORY ROLL-FORWARD & COGS CONTROL
A2: September 2026 | illustrative food manufacturing / distribution group | closing roll-forward = opening + purchases/production + transfers
A4: Category | B4: Opening Balance | C4: Purchases / Production | D4: Transfers In/(Out) | E4: Expected Closing | F4: Subledger Closing | G4: Residual Difference | H4: Status | I4: Investigation Focus
A5: Raw materials / ingredients | B5: 215000 | C5: 480000 | D5: -12000 | E5: =B5+C5+D5 | F5: 681500 | G5: =E5-F5 | H5: =IF(ABS(G5)<0.01,"Reconciled","Investigate") | I5: Goods in transit, receipt cut-off, supplier invoice matching
A6: Work in progress | B6: 98000 | C6: 365000 | D6: 5000 | E6: =B6+C6+D6 | F6: 470000 | G6: =E6-F6 | H6: =IF(ABS(G6)<0.01,"Reconciled","Investigate") | I6: Production orders, yield, labour/overhead absorption and cut-off
A7: Finished goods | B7: 425000 | C7: 690000 | D7: 7000 | E7: =B7+C7+D7 | F7: 1120000 | G7: =E7-F7 | H7: =IF(ABS(G7)<0.01,"Reconciled","Investigate") | I7: Finished goods dispatches, production completion and stocktake
A8: Packaging materials | B8: 74000 | C8: 128000 | D8: 0 | E8: =B8+C8+D8 | F8: 202000 | G8: =E8-F8 | H8: =IF(ABS(G8)<0.01,"Reconciled","Investigate") | I8: Packaging issues to production, damaged stock and usage
A9: Total inventory | B9: =SUM(B5:B8) | C9: =SUM(C5:C8) | D9: =SUM(D5:D8) | E9: =SUM(E5:E8) | F9: =SUM(F5:F8) | G9: =SUM(G5:G8) | H9: =IF(ABS(G9)<0.01,"Reconciled","Investigate") | I9: Investigate category differences before posting adjustments.
A12: COGS bridge component | B12: Amount | C12: Control / evidence
A13: Opening inventory | B13: =B9 | C13: Agree to prior month signed-off inventory balance.
A14: Purchases / production | B14: =C9 | C14: Agree to AP, production costing and receipt records.
A15: Transfers net | B15: =D9 | C15: Agree transfer records; eliminate internal movements from group totals where relevant.
A16: Less closing inventory | B16: =-F9 | C16: Agree to inventory subledger and valuation support.
A17: Indicative COGS bridge | B17: =SUM(B13:B16) | C17: Bridge is illustrative; reconcile to reported COGS and investigate any residual.

Sheet Fixed Assets
A1: FIXED ASSET REGISTER & DEPRECIATION
A2: Illustrative straight-line method; confirm accounting policy, componentisation, commencement convention and impairment requirements
A4: Asset ID | B4: Entity | C4: Asset Description | D4: In-Service Date | E4: Cost | F4: Residual Value | G4: Useful Life (Years) | H4: Monthly Depreciation | I4: Months Depreciated* | J4: Accumulated Depreciation | K4: Net Book Value | L4: Evidence Ref
A5: FA-001 | B5: VIC Manufacturing | C5: Packaging line | D5: 45474 | E5: 480000 | F5: 20000 | G5: 10 | H5: =MAX(0,(E5-F5)/(G5*12)) | I5: =MIN(G5*12,MAX(0,(YEAR(DATE(2026,9,30))-YEAR(D5))*12+MONTH(DATE(2026,9,30))-MONTH(D5))) | J5: =MIN(E5-F5,H5*I5) | K5: =MAX(F5,E5-J5) | L5: FA-INV-001
A6: FA-002 | B6: VIC Manufacturing | C6: Forklift | D6: 45703 | E6: 65000 | F6: 5000 | G6: 5 | H6: =MAX(0,(E6-F6)/(G6*12)) | I6: =MIN(G6*12,MAX(0,(YEAR(DATE(2026,9,30))-YEAR(D6))*12+MONTH(DATE(2026,9,30))-MONTH(D6))) | J6: =MIN(E6-F6,H6*I6) | K6: =MAX(F6,E6-J6) | L6: FA-INV-002
A7: FA-003 | B7: NSW Distribution | C7: Warehouse racking | D7: 45200 | E7: 210000 | F7: 10000 | G7: 10 | H7: =MAX(0,(E7-F7)/(G7*12)) | I7: =MIN(G7*12,MAX(0,(YEAR(DATE(2026,9,30))-YEAR(D7))*12+MONTH(DATE(2026,9,30))-MONTH(D7))) | J7: =MIN(E7-F7,H7*I7) | K7: =MAX(F7,E7-J7) | L7: FA-INV-003
A8: FA-004 | B8: QLD Sales & Distribution | C8: Delivery vehicle | D8: 45901 | E8: 72000 | F8: 12000 | G8: 5 | H8: =MAX(0,(E8-F8)/(G8*12)) | I8: =MIN(G8*12,MAX(0,(YEAR(DATE(2026,9,30))-YEAR(D8))*12+MONTH(DATE(2026,9,30))-MONTH(D8))) | J8: =MIN(E8-F8,H8*I8) | K8: =MAX(F8,E8-J8) | L8: FA-INV-004
A9: FA-005 | B9: VIC Manufacturing | C9: Quality testing equipment | D9: 46113 | E9: 96000 | F9: 6000 | G9: 8 | H9: =MAX(0,(E9-F9)/(G9*12)) | I9: =MIN(G9*12,MAX(0,(YEAR(DATE(2026,9,30))-YEAR(D9))*12+MONTH(DATE(2026,9,30))-MONTH(D9))) | J9: =MIN(E9-F9,H9*I9) | K9: =MAX(F9,E9-J9) | L9: FA-INV-005
A10: FA-006 | B10: NSW Distribution | C10: Refrigeration unit | D10: 46266 | E10: 144000 | F10: 9000 | G10: 9 | H10: =MAX(0,(E10-F10)/(G10*12)) | I10: =MIN(G10*12,MAX(0,(YEAR(DATE(2026,9,30))-YEAR(D10))*12+MONTH(DATE(2026,9,30))-MONTH(D10))) | J10: =MIN(E10-F10,H10*I10) | K10: =MAX(F10,E10-J10) | L10: FA-INV-006
A12: Portfolio total | E12: =SUM(E5:E10) | H12: =SUM(H5:H10) | J12: =SUM(J5:J10) | K12: =SUM(K5:K10)
A14: *Months depreciated | B14: Simplified full-month convention to September 2026; adjust to the entity's approved policy and verify in-service evidence.

Sheet CAPEX Analysis
A1: CAPITAL EXPENDITURE | PROJECT CONTROL
A2: Remaining forecast = approved budget - actual spend - committed spend; negative balance flags potential overrun
A4: Project ID | B4: Entity | C4: Project | D4: Approved Budget | E4: Actual Spend | F4: Committed Spend | G4: Remaining Forecast | H4: Utilisation % | I4: Status / Action
A5: CX-101 | B5: VIC Manufacturing | C5: Packaging line upgrade | D5: 650000 | E5: 410000 | F5: 155000 | G5: =D5-E5-F5 | H5: =IFERROR((E5+F5)/D5,0) | I5: =IF(G5<0,"Potential overrun",IF(H5>=0.9,"High utilisation","Within budget"))
A6: CX-102 | B6: NSW Distribution | C6: Warehouse automation | D6: 420000 | E6: 265000 | F6: 90000 | G6: =D6-E6-F6 | H6: =IFERROR((E6+F6)/D6,0) | I6: =IF(G6<0,"Potential overrun",IF(H6>=0.9,"High utilisation","Within budget"))
A7: CX-103 | B7: QLD Sales & Distribution | C7: Fleet replacement | D7: 180000 | E7: 132000 | F7: 25000 | G7: =D7-E7-F7 | H7: =IFERROR((E7+F7)/D7,0) | I7: =IF(G7<0,"Potential overrun",IF(H7>=0.9,"High utilisation","Within budget"))
A8: CX-104 | B8: VIC Manufacturing | C8: Quality lab equipment | D8: 125000 | E8: 56000 | F8: 32000 | G8: =D8-E8-F8 | H8: =IFERROR((E8+F8)/D8,0) | I8: =IF(G8<0,"Potential overrun",IF(H8>=0.9,"High utilisation","Within budget"))
A9: CX-105 | B9: Group Head Office | C9: ERP / finance systems | D9: 300000 | E9: 98000 | F9: 125000 | G9: =D9-E9-F9 | H9: =IFERROR((E9+F9)/D9,0) | I9: =IF(G9<0,"Potential overrun",IF(H9>=0.9,"High utilisation","Within budget"))
A10: CX-106 | B10: NSW Distribution | C10: Refrigeration upgrade | D10: 240000 | E10: 196000 | F10: 52000 | G10: =D10-E10-F10 | H10: =IFERROR((E10+F10)/D10,0) | I10: =IF(G10<0,"Potential overrun",IF(H10>=0.9,"High utilisation","Within budget"))
A11: Portfolio total | D11: =SUM(D5:D10) | E11: =SUM(E5:E10) | F11: =SUM(F5:F10) | G11: =SUM(G5:G10) | H11: =IFERROR((E11+F11)/D11,0) | I11: =IF(G11<0,"Potential overrun","Within total budget")

Sheet Close Checklist
A1: MONTH-END CLOSE CHECKLIST
A2: Proposed seven-business-day close | sample owners, statuses and evidence references; not a real close record
A4: Task ID | B4: Close Activity | C4: Owner Role | D4: Due Date | E4: Status | F4: Evidence / Reference | G4: Reviewer Notes
A5: MC-01 | B5: Post recurring journals | C5: Financial Accountant | D5: 46297 | E5: Complete | F5: JE-SEP26-001 | G5: Verify approved support and posting batch.
A6: MC-02 | B6: Reconcile bank accounts | C6: Accountant | D6: 46297 | E6: Complete | F6: BANK-REC-SEP26 | G6: Agree statement, outstanding items and GL.
A7: MC-03 | B7: Reconcile AR and AP control accounts | C7: Accountant | D7: 46298 | E7: In progress | F7: AR-AP-SEP26 | G7: Clear material reconciling items; confirm ageing agrees to GL.
A8: MC-04 | B8: Review inventory valuation and cut-off | C8: Inventory Accountant | D8: 46299 | E8: Not started | F8: INV-ROLLFWD-SEP26 | G8: Tie subledger to GL; review damaged/obsolete stock.
A9: MC-05 | B9: Update fixed asset register and depreciation | C9: Financial Accountant | D9: 46299 | E9: In progress | F9: FA-REG-SEP26 | G9: Review additions, disposals, useful lives and in-service dates.
A10: MC-06 | B10: Review accruals and prepayments | C10: Financial Accountant | D10: 46300 | E10: Not started | F10: ACCR-PREPAY-SEP26 | G10: Check completeness, service periods and reversals.
A11: MC-07 | B11: Prepare entity P&L and variance commentary | C11: Management Accountant | D11: 46301 | E11: Not started | F11: P&L-SEP26 | G11: Explain material variances using ledger and operational evidence.
A12: MC-08 | B12: Review intercompany and consolidation entries | C12: Group Accountant | D12: 46301 | E12: Not started | F12: IC-SEP26 | G12: Agree counterparties and document eliminations.
A13: MC-09 | B13: Financial Controller review and sign-off | C13: Financial Controller | D13: 46302 | E13: Not started | F13: CLOSE-SIGNOFF-SEP26 | G13: Review material estimates, open items and final reporting pack.
A15: Completion rate | B15: =COUNTIF(E5:E13,"Complete")/COUNTA(A5:A13)

Sheet Journal Register
A1: ILLUSTRATIVE JOURNAL REGISTER
A2: Balanced sample journals for demonstration only; do not post without source evidence, accounting assessment and approval
A4: Journal ID | B4: Date | C4: Entity | D4: Account | E4: Description | F4: Debit | G4: Credit | H4: Net (Dr-Cr) | I4: Support / rationale | J4: Approval Status
A5: JE-001 | B5: 46295 | C5: Group Head Office | D5: Utilities expense | E5: September utilities accrual | F5: 18500 | G5: 0 | H5: =F5-G5 | I5: Estimate based on supplier/service evidence; reverse next period if policy requires. | J5: Draft
A6: JE-001 | B6: 46295 | C6: Group Head Office | D6: Accrued expenses | E6: September utilities accrual | F6: 0 | G6: 18500 | H6: =F6-G6 | I6: Estimate based on supplier/service evidence; reverse next period if policy requires. | J6: Draft
A7: JE-002 | B7: 46295 | C7: VIC Manufacturing | D7: Depreciation expense | E7: Monthly depreciation | F7: 7800 | G7: 0 | H7: =F7-G7 | I7: Tie to approved fixed asset register and depreciation policy. | J7: Draft
A8: JE-002 | B8: 46295 | C8: VIC Manufacturing | D8: Accumulated depreciation | E8: Monthly depreciation | F8: 0 | G8: 7800 | H8: =F8-G8 | I8: Tie to approved fixed asset register and depreciation policy. | J8: Draft
A9: JE-003 | B9: 46295 | C9: NSW Distribution | D9: Inventory write-down expense | E9: Illustrative damaged stock write-down | F9: 6200 | G9: 0 | H9: =F9-G9 | I9: Only post if stocktake/NRV evidence supports adjustment and approval is obtained. | J9: Pending evidence
A10: JE-003 | B10: 46295 | C10: NSW Distribution | D10: Inventory | E10: Illustrative damaged stock write-down | F10: 0 | G10: 6200 | H10: =F10-G10 | I10: Only post if stocktake/NRV evidence supports adjustment and approval is obtained. | J10: Pending evidence
A12: Journal control | B12: Total debits | C12: =SUM(F5:F10) | D12: Total credits | E12: =SUM(G5:G10) | F12: Net difference | G12: =C12-E12

Sheet Audit & ABS
A1: AUDIT EVIDENCE & ABS SUBMISSION TRACKER
A2: Illustrative tracker only; confirm current survey instructions, definitions, reporting unit and reporting period before real submission
A4: Ref | B4: Workstream | C4: Request / Deliverable | D4: Period | E4: Owner Role | F4: Status | G4: Evidence / Validation Notes
A5: AUD-01 | B5: External audit | C5: Trial balance tied to signed-off general ledger | D5: FY2026 | E5: Financial Accountant | F5: In progress | G5: Reconcile totals and retain version-controlled export.
A6: AUD-02 | B6: External audit | C6: Fixed asset additions and disposals sample | D6: FY2026 | E6: Accountant | F6: Not started | G6: Invoices, approvals, in-service evidence and disposal support.
A7: AUD-03 | B7: External audit | C7: Bank confirmations and year-end reconciliation | D7: 30-Jun-2026 | E7: Treasury / Accountant | F7: Not started | G7: Tie confirmation to ledger and explain reconciling items.
A8: AUD-04 | B8: External audit | C8: Inventory existence and valuation support | D8: 30-Jun-2026 | E8: Inventory Accountant | F8: Not started | G8: Stock count, cut-off testing, valuation methodology and provisions.
A9: ABS-01 | B9: ABS reporting | C9: Confirm survey scope and applicable reporting unit | D9: Sep-2026 | E9: Finance Manager | F9: Not started | G9: Use official instructions; do not assume entity mapping.
A10: ABS-02 | B10: ABS reporting | C10: Reconcile turnover and employment figures to source systems | D10: Sep-2026 | E10: Finance Analyst | F10: Not started | G10: Retain source extracts, definitions, sign-off and submission receipt.
A11: ABS-03 | B11: Governance | C11: Independent review of submitted figures | D11: Sep-2026 | E11: Financial Controller | F11: Not started | G11: Document preparer/reviewer and final submitted version.

Sheet Process Improvement
A1: FINANCE PROCESS IMPROVEMENT LOG
A2: Illustrative hypotheses; quantify benefits against a baseline and validate controls before deployment
A4: ID | B4: Opportunity | C4: Current Issue / Hypothesis | D4: Proposed Action | E4: Priority | F4: Estimated Hours Saved / Month | G4: Status | H4: Success Measure | I4: Control / Risk
A5: PI-01 | B5: Automate recurring reconciliations | C5: Manual copy/paste increases review time and error risk. | D5: Use Power Query to standardise source files, map accounts and flag unmatched records; preserve source lineage. | E5: High | F5: 8 | G5: Proposed | H5: Hours per close; unresolved recon items | I5: Validate source totals, mapping, access and reviewer sign-off.
A6: PI-02 | B6: CAPEX reporting standardisation | C6: Project spend arrives in inconsistent formats. | D6: Use project IDs and a monthly roll-forward for budget, actuals, commitments and forecast-to-complete. | E6: High | F6: 5 | G6: In progress | H6: On-time reporting; forecast variance | I6: Reconcile report totals to GL/AP and approved purchase orders.
A7: PI-03 | B7: Close calendar ownership | C7: Tasks/evidence are tracked across email. | D7: Create a shared close checklist with owners, due dates, evidence links and escalation rules. | E7: Medium | F7: 4 | G7: Proposed | H7: Close duration; overdue tasks | I7: Role-based access and immutable review evidence where possible.
A8: PI-04 | B8: AI-assisted variance commentary | C8: First drafts take time and may be inconsistent. | D8: Use approved AI tools on permitted, non-sensitive extracts; require source-backed review and approval. | E8: Medium | F8: 3 | G8: Proposed | H8: Preparation time; correction rate | I8: No confidential uploads to unapproved tools; human validation mandatory.
A9: PI-05 | B9: Fixed asset data quality | C9: Missing dates/useful lives delay depreciation review. | D9: Add required-field checks and monthly exception report. | E9: Medium | F9: 2 | G9: Proposed | H9: Register completeness; depreciation corrections | I9: Restrict changes and retain approved asset forms.

Sheet PowerBI Data
A1: POWER BI FACT DATA
A2: Long-format monthly fact table; import into Power BI and use Month, Entity, Metric, Scenario, Amount
A4: Month | B4: Entity | C4: Metric | D4: Scenario | E4: Amount | F4: Currency | G4: Data Type
A5: 2026-09-30 | B5: VIC Manufacturing | C5: Revenue | D5: Actual | E5: 2450000 | F5: AUD | G5: Illustrative
A6: 2026-09-30 | B6: VIC Manufacturing | C6: Revenue | D6: Budget | E6: 2380000 | F6: AUD | G6: Illustrative
A7: 2026-09-30 | B7: VIC Manufacturing | C7: COGS | D7: Actual | E7: 1470000 | F7: AUD | G7: Illustrative
A8: 2026-09-30 | B8: VIC Manufacturing | C8: COGS | D8: Budget | E8: 1428000 | F8: AUD | G8: Illustrative
A9: 2026-09-30 | B9: VIC Manufacturing | C9: Operating Expenses | D9: Actual | E9: 510000 | F9: AUD | G9: Illustrative
A10: 2026-09-30 | B10: VIC Manufacturing | C10: Operating Expenses | D10: Budget | E10: 495000 | F10: AUD | G10: Illustrative
A11: 2026-09-30 | B11: VIC Manufacturing | C11: EBITDA | D11: Actual | E11: 470000 | F11: AUD | G11: Illustrative
A12: 2026-09-30 | B12: VIC Manufacturing | C12: EBITDA | D12: Budget | E12: 457000 | F12: AUD | G12: Illustrative
A13: 2026-09-30 | B13: NSW Distribution | C13: Revenue | D13: Actual | E13: 1280000 | F13: AUD | G13: Illustrative
A14: 2026-09-30 | B14: NSW Distribution | C14: Revenue | D14: Budget | E14: 1320000 | F14: AUD | G14: Illustrative
A15: 2026-09-30 | B15: NSW Distribution | C15: COGS | D15: Actual | E15: 806000 | F15: AUD | G15: Illustrative
A16: 2026-09-30 | B16: NSW Distribution | C16: COGS | D16: Budget | E16: 831600 | F16: AUD | G16: Illustrative
... A36: 2026-09-30 | B36: Group Head Office | C36: EBITDA | D36: Budget | E36: -250000 | F36: AUD | G36: Illustrative
